README.rst
setup.py
django_proxysql/__init__.py
django_proxysql/manage.py
django_proxysql/version.py
django_proxysql.egg-info/PKG-INFO
django_proxysql.egg-info/SOURCES.txt
django_proxysql.egg-info/dependency_links.txt
django_proxysql.egg-info/top_level.txt
django_proxysql/backends/__init__.py
django_proxysql/backends/proxysql/__init__.py
django_proxysql/backends/proxysql/base.py
django_proxysql/django_proxysql/__init__.py
django_proxysql/django_proxysql/settings.py
django_proxysql/django_proxysql/urls.py
django_proxysql/django_proxysql/wsgi.py
django_proxysql/main/__init__.py
django_proxysql/main/models.py
django_proxysql/main/tests.py