Metadata-Version: 1.1
Name: django-proxysql
Version: 0.8
Summary: A software load balancer for your Django database.
Home-page: http://github.com/btimby/django-proxysql/
Author: Ben Timby
Author-email: btimby@gmail.com
License: MIT
Platform: UNKNOWN
Classifier: Development Status :: 4 - Beta
Classifier: Intended Audience :: Developers
Classifier: Operating System :: OS Independent
Classifier: Programming Language :: Python :: 2
Classifier: Programming Language :: Python :: 3
Classifier: Topic :: Software Development :: Libraries :: Python Modules
